{"item_prop":[{"multi":false,"must":true,"name":"\u54c1\u724c","pid":20000,"prop_values":{"prop_value":[{"name":"Auanbei\/\u5965\u6602\u84d3","vid":895952633},{"is_parent":true,"name":"CHIC","vid":37282},{"is_parent":true,"name":"D.seven","vid":11175712},{"is_parent":true,"name":"DAIRNIM\/\u9edb\u5c14\u5c3c\u66fc","vid":304270591},{"name":"DIGITALJAZZ\/\u6570\u5b57\u7235\u58eb","vid":1205080536},{"name":"FUNRE\/\u5e06\u777f","vid":1111402845},{"name":"GPP","vid":3621574},{"is_parent":true,"name":"GUOER\/\u679c\u513f\u7535\u5b50","vid":139809977},{"name":"JAKCOM","vid":1010662583},{"is_parent":true,"name":"KUSHOP","vid":76865714},{"name":"LANWK\/\u6717\u552f\u79d1","vid":26061280},{"name":"LCDG","vid":65844926},{"is_parent":true,"name":"Lamyik","vid":123684370},{"is_parent":true,"name":"MANDERM\/\u66fc\u5fb7\u7f8e","vid":217124309},{"is_parent":true,"name":"MATE","vid":6755779},{"name":"MOUXIC\/\u6155\u661f","vid":772326810},{"name":"MYKIMO\/\u8fc8\u5947\u9b54","vid":46040583},{"name":"NEWPLAN","vid":115112435},{"name":"NOOSY","vid":68766206},{"is_parent":true,"name":"OSGEER\/\u5965\u65af\u683c\u5c14","vid":108657051},{"is_parent":true,"name":"PRANO\/\u535a\u96c5\u8bfa","vid":156921545},{"is_parent":true,"name":"PueriLe\/\u76ae\u4e9a\u4e50","vid":149827497},{"is_parent":true,"name":"QinD\/\u52e4\u5927","vid":84583193},{"name":"RANVOO","vid":206054053},{"name":"RGKNSE","vid":100335965},{"name":"ROVDOO","vid":1060086031},{"name":"Remax\/\u777f\u91cf","vid":85384125},{"name":"Robotsky","vid":1331428697},{"name":"SAYHAY","vid":912384188},{"is_parent":true,"name":"SINLIHE","vid":146554053},{"is_parent":true,"name":"SSK\/\u98da\u738b","vid":30811},{"name":"SUNG-LL\/\u5c1a\u7406","vid":1336939265},{"name":"Stne\/\u6eda\u77f3","vid":115705660},{"name":"TAMGLE","vid":134076361},{"name":"TIKITAKA","vid":933170258},{"name":"TORRAS\/\u56fe\u62c9\u65af","vid":16374678},{"is_parent":true,"name":"Tadpole\/\u874c\u86aa\u7535\u5b50","vid":82886639},{"name":"XGE","vid":32408560},{"is_parent":true,"name":"ZERORO\/\u8d5b\u7f57\u7f57","vid":94602788},{"name":"betashu\/\u8d1d\u5854\u8700","vid":834338022},{"name":"binwoo\/\u7f24\u8d2d","vid":366886636},{"is_parent":true,"name":"ginkgonut\/\u767d\u679c","vid":113383335},{"name":"i-smartsim","vid":28788080},{"name":"i-supersim","vid":185066039},{"name":"kindtoy\/\u9cb8\u62d3","vid":36795434},{"name":"kinple\/\u91d1\u679c\u529b","vid":193708040},{"is_parent":true,"name":"micro","vid":3433734},{"is_parent":true,"name":"oksense","vid":134474730},{"name":"taozu","vid":5920716},{"name":"\u4eae\u9f99","vid":11675927},{"is_parent":true,"name":"\u4f1f\u68ee","vid":9949009},{"name":"\u521b\u4f70\u4ebf","vid":869762981},{"name":"\u535a\u529b\u9ad8","vid":13066028},{"name":"\u5361\u5176\u745f","vid":229058540},{"name":"\u54c8\u5bc6\u65af","vid":966596216},{"name":"\u597d\u6382","vid":528056559},{"name":"\u5c24\u5176\u9f99","vid":132521313},{"name":"\u6052\u96c5\u8fbe","vid":13476897},{"name":"\u6469\u627f","vid":553168112},{"is_parent":true,"name":"\u6b27\u80e4","vid":137756418},{"name":"\u6d1b\u987f","vid":119295427},{"name":"\u7231\u6676\u8fbe","vid":6066252},{"name":"\u76f8\u7f18","vid":45120820},{"name":"\u7834\u7af9","vid":127419517},{"name":"\u7b2c\u4e5d\u5143\u7d20","vid":21285514},{"is_parent":true,"name":"\u806a\u660e\u9f20","vid":6338220},{"is_parent":true,"name":"\u8fe6\u5361\u4ed5","vid":335064192},{"name":"\u9177\u5f7c","vid":296210535},{"name":"\u95ea\u9a70","vid":49926973},{"name":"\u9e3f\u6d6a","vid":7896423}]}}]}