{"item_prop":[{"multi":false,"must":false,"name":"\u54c1\u724c","pid":20000,"prop_values":{"prop_value":[{"name":"3142","vid":3377680},{"name":"ADAM","vid":3346808},{"name":"ADAMII","vid":47366446},{"name":"AYEAH\/\u54c8\u91ce","vid":1117206816},{"name":"BCE","vid":3474548},{"name":"BLP\/\u6807\u529b","vid":77734141},{"name":"Buck series","vid":146650656},{"name":"CUESOUL","vid":605840333},{"name":"Condy","vid":44019757},{"name":"Cuetec","vid":7166604},{"name":"Cuppa","vid":39837666},{"name":"DLP","vid":81172},{"name":"Dave Coutts\/\u6234\u592b\u5e93\u8328","vid":299410332},{"name":"Dufferin","vid":10413931},{"name":"EARTHLITE","vid":60984506},{"name":"EDITH\/\u4f0a\u8482\u4e1d","vid":259490042},{"name":"FUT","vid":4342542},{"name":"Goko\/\u6208\u5974","vid":48567017},{"name":"HUNT & CUSTOM","vid":1081090672},{"name":"Hiboy Cue","vid":77150110},{"name":"JAGUAR","vid":3379659},{"name":"JEZZ","vid":66314392},{"name":"JIANJIANG","vid":9337182},{"name":"JOSS","vid":4011319},{"name":"JOSSII","vid":115600408},{"name":"KANGHOM\/\u5eb7\u6cd3","vid":217674648},{"name":"LEO","vid":3279863},{"name":"LK\uff0eT","vid":87741557},{"name":"LP\uff08\u8fd0\u52a8\u7528\u54c1\uff09","vid":1133136723},{"name":"Luwint","vid":23592062},{"name":"Mike Wooldridge","vid":7100720},{"name":"Musashi\/\u6b66\u85cf","vid":91958623},{"name":"N9","vid":26795},{"name":"Oxhorn","vid":97257970},{"name":"PERI\/\u76ae\u5c14\u529b","vid":3331711},{"name":"PROFESSIONAL CUES FALCON","vid":647918822},{"name":"PROROCKET\/\u804c\u4e1a\u706b\u7bad","vid":813812854},{"name":"Poinos","vid":224770555},{"name":"ROBIN COOK","vid":18677245},{"name":"SHANGYU\/\u5c1a\u5a31","vid":922858157},{"name":"SLP","vid":113377551},{"name":"SOUTH WEST CUES","vid":119079538},{"name":"Trevor White","vid":20715429},{"name":"UTTU\/\u4e4c\u56fe","vid":645052681},{"name":"Unique Cues","vid":158773523},{"name":"Universal Billiard","vid":73016451},{"name":"WELLY","vid":19282729},{"name":"WINOMIN\/\u50b2\u54c1","vid":1126484808},{"name":"WOOD FOrce","vid":127517441},{"name":"Y.C POWER","vid":9110035},{"name":"Z(\u7403\u6746)","vid":1105584964},{"name":"dynamic ball\/\u7403\u52a8\u529b","vid":679350033},{"name":"fury","vid":6112076},{"name":"gf\/\u9ad8\u592b","vid":3305573},{"name":"rattler\/\u54cd\u5c3e\u86c7","vid":1088784250},{"name":"stephen david","vid":278344478},{"name":"\u4e09\u65af\u535a\u7279","vid":76049595},{"name":"\u4e18\u6cf0\u514b","vid":8046382},{"name":"\u5065\u82f1","vid":3379517},{"name":"\u53f0\u9738","vid":120887269},{"name":"\u54c1\u5948","vid":98356470},{"name":"\u5eb7\u5e1d","vid":7404598},{"name":"\u661f\u724c","vid":109480},{"name":"\u661f\u8fea","vid":20006979},{"name":"\u6765\u529b\u724c","vid":73016221},{"name":"\u68d2\u8fea","vid":27960633},{"name":"\u6fb3\u83b1\u7279","vid":25972694},{"name":"\u72fc\u70df\u53f0","vid":1096546695},{"name":"\u7687\u51a0","vid":42256},{"name":"\u79d1\u5965\u514b","vid":913078760},{"name":"\u80dc\u4ed5","vid":34106369},{"name":"\u98de\u8fbe","vid":3227286},{"name":"B\uff0eS","vid":131756},{"name":"LP","vid":50727},{"name":"MEZZ(\u65e5\u672c)","vid":132201},{"name":"Master(\u6cf0\u56fd)","vid":132199},{"name":"Omin(\u6cf0\u56fd)","vid":132198},{"name":"O\u2019Min\/\u5965\u79d8","vid":87739594},{"name":"Riley","vid":132202},{"name":"Yasaka\/\u4e9a\u8428\u5361","vid":30241},{"name":"\u67ab\u53f6(\u52a0\u62ff\u5927)","vid":132200},{"name":"\u7f8e\u6d32\u8c79(\u7f8e\u56fd)","vid":132197},{"name":"\u5a01\u739b\u65af","vid":27039364},{"name":"other\/\u5176\u4ed6","vid":29534},{"name":"Collapsar\/\u9ed1\u6d1e","vid":9667086},{"name":"TB \u817e\u52c3","vid":122837532}]}},{"multi":true,"must":false,"name":"\u989c\u8272\u5206\u7c7b","pid":1627207,"prop_values":{"prop_value":[{"name":"\u4e73\u767d\u8272","vid":28321},{"name":"\u519b\u7eff\u8272","vid":3232483},{"name":"\u5361\u5176\u8272","vid":28331},{"name":"\u5496\u5561\u8272","vid":129819},{"name":"\u58a8\u7eff\u8272","vid":80557},{"name":"\u5929\u84dd\u8272","vid":3232484},{"name":"\u59dc\u9ec4\u8272","vid":15409374},{"name":"\u5b54\u96c0\u84dd","vid":5138330},{"name":"\u5b9d\u84dd\u8272","vid":3707775},{"name":"\u5de7\u514b\u529b\u8272","vid":3232481},{"name":"\u660e\u9ec4\u8272","vid":20412615},{"name":"\u674f\u8272","vid":30155},{"name":"\u67e0\u6aac\u9ec4","vid":132476},{"name":"\u6817\u8272","vid":6071353},{"name":"\u6854\u7ea2\u8272","vid":4950473},{"name":"\u6854\u8272","vid":90554},{"name":"\u6d45\u68d5\u8272","vid":30158},{"name":"\u6d45\u7070\u8272","vid":28332},{"name":"\u6d45\u7d2b\u8272","vid":4104877},{"name":"\u6d45\u7eff\u8272","vid":30156},{"name":"\u6d45\u84dd\u8272","vid":28337},{"name":"\u6d45\u9ec4\u8272","vid":60092},{"name":"\u6df1\u5361\u5176\u5e03\u8272","vid":3232482},{"name":"\u6df1\u68d5\u8272","vid":6588790},{"name":"\u6df1\u7070\u8272","vid":3232478},{"name":"\u6df1\u7d2b\u8272","vid":3232479},{"name":"\u6df1\u84dd\u8272","vid":28340},{"name":"\u6e56\u84dd\u8272","vid":5483105},{"name":"\u7070\u8272","vid":28334},{"name":"\u73ab\u7ea2\u8272","vid":3594022},{"name":"\u767d\u8272","vid":28320},{"name":"\u7c73\u767d\u8272","vid":4266701},{"name":"\u7c89\u7ea2\u8272","vid":3232480},{"name":"\u7d2b\u7ea2\u8272","vid":5167321},{"name":"\u7d2b\u7f57\u5170","vid":80882},{"name":"\u7d2b\u8272","vid":28329},{"name":"\u7ea2\u8272","vid":28326},{"name":"\u7eff\u8272","vid":28335},{"name":"\u7fe0\u7eff\u8272","vid":8588036},{"name":"\u82b1\u8272","vid":130164},{"name":"\u8367\u5149\u7eff","vid":6535235},{"name":"\u8367\u5149\u9ec4","vid":6134424},{"name":"\u84dd\u8272","vid":28338},{"name":"\u85cf\u9752\u8272","vid":28866},{"name":"\u85d5\u8272","vid":4464174},{"name":"\u8910\u8272","vid":132069},{"name":"\u897f\u74dc\u7ea2","vid":3743025},{"name":"\u900f\u660e","vid":107121},{"name":"\u9152\u7ea2\u8272","vid":28327},{"name":"\u91d1\u8272","vid":28328},{"name":"\u94f6\u8272","vid":28330},{"name":"\u9752\u8272","vid":3455405},{"name":"\u9999\u69df\u8272","vid":130166},{"name":"\u9a7c\u8272","vid":3224419},{"name":"\u9ec4\u8272","vid":28324},{"name":"\u9ed1\u8272","vid":28341}]}},{"multi":false,"must":false,"name":"\u53f0\u7403\u6746\u7ed3\u6784","pid":5896336,"prop_values":{"prop_value":[{"name":"\u5355\u652f\u7403\u6746","vid":325274610},{"name":"3\/4\u5206\u4f53\u7403\u6746","vid":325274608},{"name":"1\/2\u5206\u4f53\u7403\u6746","vid":57456347},{"name":"4\/5\u5206\u4f53\u7403\u6746","vid":57456348},{"name":"3\/4\u9ad8\u4f4d\u5206\u4f53\u7403\u6746","vid":57456349},{"name":"\u5176\u4ed6","vid":20213}]}},{"multi":false,"must":false,"name":"\u6750\u8d28","pid":20021,"prop_values":{"prop_value":[{"name":"\u6a61\u6728","vid":105108},{"name":"\u67ab\u6728","vid":3728576},{"name":"\u767d\u8721\u6728","vid":109395},{"name":"\u78b3\u7d20","vid":3348356},{"name":"\u9ed1\u6a80","vid":8761682},{"name":"\u5176\u4ed6","vid":20213}]}},{"multi":false,"must":false,"name":"\u7403\u6746\u5206\u7c7b","pid":122216821,"prop_values":{"prop_value":[{"name":"\u51b2\u6746(\u5f00\u7403\u7528\u6746)","vid":57464154},{"name":"\u8df3\u6746","vid":75137512},{"name":"\u51b2\u8df3\u6746","vid":7532365},{"name":"\u65af\u8bfa\u514b\u7403\u6746","vid":11211427},{"name":"\u4e5d\u7403\u7403\u6746","vid":57464157},{"name":"\u5176\u4ed6","vid":20213}]}},{"multi":false,"must":false,"name":"\u53f0\u7403\u6253\u6cd5","pid":5896293,"prop_values":{"prop_value":[{"name":"\u82f1\u5f0f\u53f0\u7403","vid":57456045},{"name":"\u7f8e\u5f0f\u53f0\u7403","vid":37589051},{"name":"\u4e2d\u5f0f\u65af\u8bfa\u514b\u53f0\u7403","vid":57456046},{"name":"\u6cd5\u5f0f\u53f0\u7403","vid":57456047},{"name":"\u5f00\u4f26\u5f0f\u53f0\u7403","vid":57456048},{"name":"\u82b1\u5f0f\u4e5d\u7403","vid":57456049}]}},{"multi":false,"must":false,"name":"\u8d27\u53f7","pid":13021751}]}