{"item_prop":[{"multi":false,"must":false,"name":"\u54c1\u724c","pid":20000,"prop_values":{"prop_value":[{"name":"Arturia","vid":90825054},{"name":"Beyond","vid":118793},{"name":"BlackRoses","vid":912268087},{"name":"Catherine\/\u51ef\u745f\u7433","vid":13030939},{"name":"Cohen","vid":31940803},{"name":"DR.J","vid":31831098},{"name":"FIRE","vid":3674703},{"name":"GEEK\/\u6781\u5ba2","vid":75394157},{"name":"HOKE","vid":14010252},{"name":"HRSD\/\u534e\u5c14\u65af\u987f","vid":245904612},{"name":"M.king","vid":113544657},{"name":"NORD","vid":18323886},{"name":"NOVATION","vid":6096893},{"name":"PianoLED\/\u4e50\u5178","vid":738760970},{"name":"STUDIOLOGIC","vid":11314172},{"name":"TJ","vid":3341709},{"name":"Vitoos","vid":109603459},{"name":"WERSI","vid":65613813},{"name":"hxw","vid":16179537},{"name":"julius feurich","vid":191296006},{"name":"\u4e91\u4e4b\u66f2","vid":316034221},{"name":"\u4f17\u73a9","vid":1027922394},{"name":"\u5b54\u96c0\u516c\u4e3b","vid":8772227},{"name":"\u62c9\u514b\u4e1d","vid":70099663},{"name":"\u65b0\u97f5","vid":3411382},{"name":"\u7ea2\u53f6","vid":137979507},{"name":"\u7f57\u4f0a","vid":7580724},{"name":"\u827e\u7c73\u4e3d","vid":3356049},{"name":"\u8a89\u58f0","vid":20269911},{"name":"\u94f6\u9c7c","vid":85448},{"name":"\u9e3f\u83ba","vid":376006499},{"name":"KAWAI\/\u5361\u74e6\u4f9d","vid":3335615},{"is_parent":true,"name":"KORG","vid":4538569},{"is_parent":true,"name":"M-AUDIO","vid":31088},{"is_parent":true,"name":"Roland\/\u7f57\u5170","vid":3384155},{"is_parent":true,"name":"Yamaha\/\u96c5\u9a6c\u54c8","vid":27207},{"is_parent":true,"name":"meirkergr\/\u7f8e\u79d1","vid":3558090}]}},{"multi":false,"must":false,"name":"\u952e\u6570","pid":122216808,"prop_values":{"prop_value":[{"name":"37\u952e","vid":13320681},{"name":"41\u952e","vid":56509846},{"name":"61\u952e","vid":21056080},{"name":"49\u952e","vid":56509847},{"name":"25\u952e","vid":56509848},{"name":"54\u952e","vid":56509849},{"name":"76\u952e","vid":56509850},{"name":"\u5176\u4ed6","vid":20213},{"name":"88\u952e","vid":12670512}]}},{"multi":false,"must":false,"name":"\u97f3\u8272\u6570","pid":5741463,"prop_values":{"prop_value":[{"name":"100\u79cd\u4ee5\u4e0b","vid":56509871},{"name":"101\u79cd(\u542b)-200\u79cd(\u542b)","vid":493280842},{"name":"201\u79cd\u4ee5\u4e0a","vid":56509874}]}},{"multi":false,"must":false,"name":"\u6700\u5927\u590d\u97f3\u6570","pid":5741455,"prop_values":{"prop_value":[{"name":"16\u4e2a","vid":14517768},{"name":"32\u4e2a","vid":40438369},{"name":"64\u4e2a","vid":115638999},{"name":"48\u4e2a","vid":27784477},{"name":"128\u4e2a","vid":67968210},{"name":"\u5176\u4ed6","vid":20213}]}},{"multi":false,"must":false,"name":"\u793a\u8303\u66f2\u6570","pid":134992239,"prop_values":{"prop_value":[{"name":"10\u9996\u4ee5\u4e0b","vid":56509865},{"name":"11-50\u9996","vid":56509866},{"name":"51-100\u9996","vid":56509869},{"name":"101\u9996\u53ca\u4ee5\u4e0a","vid":56509870}]}}]}