{"item_prop":[{"multi":false,"must":true,"name":"\u54c1\u724c","pid":20000,"prop_values":{"prop_value":[{"name":"BAKER HUGHES\/\u8d1d\u514b\u4f11\u65af","vid":848468127},{"name":"DECORATOR\/\u88c5\u4fee\u5de5","vid":869772327},{"name":"DOMELE\/\u591a\u7c73\u4e50","vid":831130978},{"is_parent":true,"name":"PALACE\/\u78a7\u4e3d","vid":262814528},{"name":"UOBOC\/\u4f18\u6ce2\u79d1","vid":992650165},{"name":"WANGLEBAO\/\u7f51\u4e50\u5b9d","vid":814212020},{"name":"XINGGUO","vid":88631929},{"name":"banksydream\/\u73ed\u514b\u65af","vid":984206429},{"name":"fuxiang paint\/\u798f\u6e58\u6f06","vid":1010782495},{"name":"samrui\/\u4e09\u745e","vid":996342272},{"name":"\u4e03\u5f69\u4e91","vid":67990},{"name":"\u4e03\u8272\u8f89","vid":71463870},{"name":"\u4e07\u78ca","vid":27279010},{"name":"\u4e39\u6167","vid":12127583},{"name":"\u4e3d\u88c5","vid":41775151},{"name":"\u4e50\u6652","vid":293970527},{"name":"\u4eac\u70b9","vid":81471405},{"name":"\u4f01\u5f3a","vid":25098827},{"name":"\u5065\u5eb7\u798f\u724c","vid":42042001},{"name":"\u5149\u5934\u5f3a(\u827a\u672f\u6f06)","vid":1386784834},{"name":"\u51a0\u724c","vid":5904406},{"name":"\u540d\u73e0","vid":29089298},{"name":"\u5471\u5471\u4eae","vid":314944299},{"name":"\u548c\u65b0","vid":9870475},{"name":"\u5723\u798f\u6765","vid":59983967},{"is_parent":true,"name":"\u591c\u660e\u4eae","vid":67410415},{"is_parent":true,"name":"\u5927\u5b9d\u6f06","vid":4540944},{"name":"\u5934\u724c\uff08\u7740\u8272\u5242\uff09","vid":1120428639},{"is_parent":true,"name":"\u5965\u5927\u6797","vid":6360992},{"name":"\u597d\u79c0\u5bb6","vid":756002109},{"name":"\u5bcc\u4e9a","vid":4031196},{"name":"\u5c45\u8c6a","vid":4068323},{"name":"\u5de5\u5320\u5927\u5e08","vid":242256665},{"name":"\u5de7\u52b2","vid":98326764},{"name":"\u5efa\u79c0","vid":107361582},{"name":"\u601d\u60f3\u8005","vid":116498274},{"name":"\u6155\u51ef\u98ce","vid":626338914},{"name":"\u6208\u7533","vid":394318592},{"name":"\u6398\u4f18","vid":197228470},{"name":"\u65e0\u7a77\u82b1","vid":104753990},{"name":"\u660c\u5947","vid":8938775},{"name":"\u660e\u8fdc","vid":17614705},{"name":"\u6668\u521b","vid":38320745},{"name":"\u695a\u7eff\u8f69","vid":236916746},{"name":"\u6b27\u5229\u7f8e","vid":34137875},{"name":"\u6caa\u5de5","vid":141232776},{"name":"\u6d01\u751f","vid":39027079},{"name":"\u6d1b\u8bd7\u5c3c","vid":627092368},{"name":"\u6d82\u9738\u67d2","vid":237268621},{"name":"\u6df1\u8fc8","vid":119698069},{"name":"\u6f06\u534e\u4ed5","vid":119755382},{"name":"\u7275\u7231","vid":58285064},{"name":"\u7389\u8299\u84c9","vid":118292423},{"name":"\u767e\u5fb7\u4e50","vid":91480833},{"name":"\u79d1\u5179","vid":94657501},{"name":"\u79e6\u74a7","vid":1036796702},{"name":"\u7c73\u6d82","vid":276632226},{"name":"\u827a\u5168","vid":95691398},{"name":"\u82cf\u683c\u4ed5","vid":71166337},{"name":"\u9053\u916c","vid":528284405},{"name":"\u90dd\u7f8e\u8fea","vid":608534950},{"is_parent":true,"name":"\u946b\u70e8","vid":15389595},{"is_parent":true,"name":"\u94ed\u7f8e","vid":17997112},{"name":"\u96c5\u5170\u58eb","vid":107820},{"name":"BAUHINIA\/\u7d2b\u8346\u82b1","vid":105282},{"name":"CARPOLY\/\u5609\u5b9d\u8389","vid":105285},{"name":"Calvin\/\u6977\u5a01","vid":50916636},{"name":"Dulux\/\u591a\u4e50\u58eb","vid":151922391},{"is_parent":true,"name":"IVY\/\u957f\u6625\u85e4","vid":105638},{"name":"NIPPON PAINT\/\u7acb\u90a6","vid":42812},{"name":"OPEL\/\u6b27\u9f99","vid":105637},{"name":"SKSHU\/\u4e09\u68f5\u6811","vid":105295},{"name":"giraffe\/\u957f\u9888\u9e7f","vid":42815},{"name":"huarun\/\u534e\u6da6\u6f06","vid":105281},{"name":"\u6c49\u9ad8\u767e\u5f97","vid":4066935},{"name":"\u82ac\u7433","vid":3585605},{"is_parent":true,"name":"\u5609\u5929\u4e0b","vid":92488300},{"name":"\u9ed1\u91d1\u94a2","vid":3762685},{"name":"\u4e50\u5e84","vid":24115712},{"name":"eastmen\/\u7231\u601d\u66fc","vid":848478287}]}},{"multi":true,"must":false,"name":"\u989c\u8272\u5206\u7c7b","pid":1627207,"prop_values":{"prop_value":[{"name":"\u4e73\u767d\u8272","vid":28321},{"name":"\u519b\u7eff\u8272","vid":3232483},{"name":"\u5361\u5176\u8272","vid":28331},{"name":"\u5496\u5561\u8272","vid":129819},{"name":"\u58a8\u7eff\u8272","vid":80557},{"name":"\u5929\u84dd\u8272","vid":3232484},{"name":"\u59dc\u9ec4\u8272","vid":15409374},{"name":"\u5b54\u96c0\u84dd","vid":5138330},{"name":"\u5b9d\u84dd\u8272","vid":3707775},{"name":"\u5de7\u514b\u529b\u8272","vid":3232481},{"name":"\u660e\u9ec4\u8272","vid":20412615},{"name":"\u674f\u8272","vid":30155},{"name":"\u67e0\u6aac\u9ec4","vid":132476},{"name":"\u6817\u8272","vid":6071353},{"name":"\u6854\u7ea2\u8272","vid":4950473},{"name":"\u6854\u8272","vid":90554},{"name":"\u6d45\u68d5\u8272","vid":30158},{"name":"\u6d45\u7070\u8272","vid":28332},{"name":"\u6d45\u7d2b\u8272","vid":4104877},{"name":"\u6d45\u7eff\u8272","vid":30156},{"name":"\u6d45\u84dd\u8272","vid":28337},{"name":"\u6d45\u9ec4\u8272","vid":60092},{"name":"\u6df1\u5361\u5176\u5e03\u8272","vid":3232482},{"name":"\u6df1\u68d5\u8272","vid":6588790},{"name":"\u6df1\u7070\u8272","vid":3232478},{"name":"\u6df1\u7d2b\u8272","vid":3232479},{"name":"\u6df1\u84dd\u8272","vid":28340},{"name":"\u6e56\u84dd\u8272","vid":5483105},{"name":"\u7070\u8272","vid":28334},{"name":"\u73ab\u7ea2\u8272","vid":3594022},{"name":"\u767d\u8272","vid":28320},{"name":"\u7c73\u767d\u8272","vid":4266701},{"name":"\u7c89\u7ea2\u8272","vid":3232480},{"name":"\u7d2b\u7ea2\u8272","vid":5167321},{"name":"\u7d2b\u7f57\u5170","vid":80882},{"name":"\u7d2b\u8272","vid":28329},{"name":"\u7ea2\u8272","vid":28326},{"name":"\u7eff\u8272","vid":28335},{"name":"\u7fe0\u7eff\u8272","vid":8588036},{"name":"\u82b1\u8272","vid":130164},{"name":"\u8367\u5149\u7eff","vid":6535235},{"name":"\u8367\u5149\u9ec4","vid":6134424},{"name":"\u84dd\u8272","vid":28338},{"name":"\u85cf\u9752\u8272","vid":28866},{"name":"\u85d5\u8272","vid":4464174},{"name":"\u8910\u8272","vid":132069},{"name":"\u897f\u74dc\u7ea2","vid":3743025},{"name":"\u900f\u660e","vid":107121},{"name":"\u9152\u7ea2\u8272","vid":28327},{"name":"\u91d1\u8272","vid":28328},{"name":"\u94f6\u8272","vid":28330},{"name":"\u9752\u8272","vid":3455405},{"name":"\u9999\u69df\u8272","vid":130166},{"name":"\u9a7c\u8272","vid":3224419},{"name":"\u9ec4\u8272","vid":28324},{"name":"\u9ed1\u8272","vid":28341}]}},{"multi":true,"must":false,"name":"\u5bb9\u91cf","pid":20138,"prop_values":{"prop_value":[{"name":"\u624b\u626b\u6f06\/\u624b\u6447\u55b7\u6f06","vid":94800763},{"name":"0-1L","vid":94800764},{"name":"1L","vid":3278822},{"name":"1.5L","vid":3278823},{"name":"2L","vid":3278824},{"name":"2.5L","vid":105673},{"name":"3L","vid":3799971},{"name":"3.5L","vid":4367460},{"name":"4L","vid":3469576},{"name":"4.5L","vid":7192093},{"name":"5L","vid":105674},{"name":"6L","vid":3263479},{"name":"7L","vid":3322201},{"name":"8L","vid":3793562},{"name":"9L","vid":5635969},{"name":"10L","vid":105675},{"name":"12L","vid":3720376},{"name":"13L","vid":6117333},{"name":"15L","vid":34999},{"name":"16L","vid":106800},{"name":"17L","vid":7714713},{"name":"18L","vid":105676},{"name":"18L\u4ee5\u4e0a","vid":94800765},{"name":"\u5176\u4ed6","vid":20213}]}},{"multi":false,"must":false,"name":"\u9002\u7528\u90e8\u4f4d","pid":10206993,"prop_values":{"prop_value":[{"name":"\u5185\u5899","vid":30651791},{"name":"\u5916\u5899","vid":30875566},{"name":"\u5730\u576a","vid":12009082},{"name":"\u5176\u4ed6\/other","vid":14863995}]}},{"multi":false,"must":false,"name":"\u6d82\u5c42\u7c7b\u522b","pid":122276062,"prop_values":{"prop_value":[{"name":"\u5e95\u6f06","vid":105647},{"name":"\u9762\u6f06","vid":9354723}]}}]}